refery/__init__.py
refery/custom_io.py
refery/main.py
refery/prettify.py
refery/test_suite.py
refery-2.1.0.dist-info/LICENSE
refery-2.1.0.dist-info/METADATA
refery-2.1.0.dist-info/WHEEL
refery-2.1.0.dist-info/entry_points.txt
refery-2.1.0.dist-info/RECORD
