Metadata-Version: 2.1
Name: refery
Version: 2.1.0
Summary: Functional testing tool
Home-page: https://github.com/RostanTabet/refery
License: MIT
Author: Rostan Tabet
Author-email: rostan.tabet@gmail.com
Requires-Python: >=3.10,<4.0
Classifier: Intended Audience :: Developers
Classifier: License :: OSI Approved :: MIT License
Classifier: Operating System :: OS Independent
Classifier: Programming Language :: Python :: 3
Classifier: Programming Language :: Python :: 3.10
Classifier: Programming Language :: Python :: 3.11
Classifier: Programming Language :: Python :: 3.12
Classifier: Topic :: Software Development :: Testing
Classifier: Topic :: Utilities
Requires-Dist: PyYAML (>=6.0.1,<7.0.0)
Requires-Dist: colorama (>=0.4.6,<0.5.0)
Requires-Dist: junit-xml (>=1.9,<2.0)
Project-URL: Bug Tracker, https://github.com/RostanTabet/refery/issues
Project-URL: Repository, https://github.com/RostanTabet/refery.git
